poola/__init__.py
poola/_modidx.py
poola/core.py
poola-0.0.20.dist-info/LICENSE
poola-0.0.20.dist-info/METADATA
poola-0.0.20.dist-info/WHEEL
poola-0.0.20.dist-info/top_level.txt
poola-0.0.20.dist-info/RECORD
