Metadata-Version: 2.1
Name: poola
Version: 0.0.20
Summary: Python package to analyze the results of pooled CRISPR screens
Home-page: https://github.com/broadinstitute/poola/tree/master/
Author: Peter DeWeirdt, Mudra Hegde
Author-email: petedeweirdt@gmail.com, mudrahegde@gmail.com
License: Apache Software License 2.0
Keywords: CRISPR,python
Classifier: Development Status :: 3 - Alpha
Classifier: Intended Audience :: Developers
Classifier: License :: OSI Approved :: Apache Software License
Classifier: Natural Language :: English
Classifier: Programming Language :: Python :: 3.6
Classifier: Programming Language :: Python :: 3.7
Classifier: Programming Language :: Python :: 3.8
Requires-Python: >=3.6
License-File: LICENSE
Requires-Dist: numpy >=1.19.5
Requires-Dist: pandas >=1.0.0
Requires-Dist: scikit-learn >=0.24.1
Requires-Dist: scipy >=1.5.2
Requires-Dist: statsmodels >=0.12.2
